[  {"id": 1, "app": "FileSharing", "pos": "begin", "path" :"C:/Users/krisc/_tf2py310/FileSharing/Source/image", "storage" : "local", "ext" : "jpg", "Case_ID" : "yes", "LogicalName" : "Human_image"},
   {"id": 4, "app": "FileSharing", "pos": "begin", "path" :"C:/Users/krisc/_tf2py310/FileSharing/Source/list", "storage" : "local", "ext" : "txt", "Case_ID" : "no",  "LogicalName" : "Human_Outfit_list"}, 
   {"id": 5, "app": "FileSharing", "pos": "begin", "path" :"C:/Users/krisc/_tf2py310/FileSharing/Source/cloth", "storage" : "local", "ext" : "jpg", "Case_ID" : "no", "LogicalName" : "Outfit_image"},  
   {"id": 6, "app": "FileSharing", "pos": "begin", "path" :"C:/Users/krisc/_tf2py310/FileSharing/Source/cloth-mask", "storage" : "local", "ext" : "jpg", "Case_ID" : "no", "LogicalName" : "Outfit_mask"},
   {"id": 10, "app": "OpenPose", "pos": "end", "foreign-id" : 1, "path" : "C:/Users/krisc/_tf2py37/openpose/examples/media", "storage" : "local", "ext" : "jpg", "time_out" : 30},
   {"id": 11, "app": "OpenPose", "pos": "begin", "path" : "C:/Users/krisc/_tf2py37/openpose/python/image", "storage" : "local", "ext" : "png", "time_out" : 30, "Case_ID" : "yes"},
   {"id": 12, "app": "OpenPose", "pos": "begin", "path" : "C:/Users/krisc/_tf2py37/openpose/python/json", "storage" : "local", "ext" : "json", "time_out" : 30, "Case_ID" : "yes"},
   {"id": 17, "app": "Graphonomy", "pos": "end", "foreign-id" : 1, "path" : "Graphonomy_input", "storage" : "cloud", "ext" : "jpg", "time_out" : 30},
   {"id": 18, "app": "Graphonomy", "pos": "begin", "path" : "img/Graphonomy_input", "storage" : "local", "ext" : "jpg", "time_out" : 30, "Case_ID" : "yes"},
   {"id": 19, "app": "Graphonomy", "pos": "begin", "path" : "Graphonomy_output", "storage" : "cloud", "ext" : "png", "time_out" : 30, "Case_ID" : "yes"},
   {"id": 20, "app": "Graphonomy", "pos": "begin", "path" : "Graphonomy_output_vis", "storage" : "cloud", "ext" : "png", "time_out" : 30, "Case_ID" : "yes"},
   {"id": 21, "app": "DensePose", "pos": "end", "foreign-id" : 1, "path" : "DensePose_input", "storage" : "cloud", "ext" : "jpg", "time_out" : 30},
   {"id": 22, "app": "DensePose", "pos": "begin", "path" : "DP/DensePose_input", "storage" : "local", "ext" : "jpg", "time_out" : 30, "Case_ID" : "yes"},
   {"id": 23, "app": "DensePose", "pos": "begin", "path" : "DensePose_output", "storage" : "cloud", "ext" : "png", "time_out" : 30, "Case_ID" : "yes"},
   {"id": 24, "app": "Parse_agnostic", "pos": "end", "foreign-id" : 1, "path" : "agnostic/image", "storage" : "cloud", "ext" : "jpg", "time_out" : 30},
   {"id": 25, "app": "Parse_agnostic", "pos": "end", "foreign-id" : 12, "path" : "agnostic/openpose_json", "storage" : "cloud", "ext" : "json", "time_out" : 30},
   {"id": 26, "app": "Parse_agnostic", "pos": "end", "foreign-id" : 19, "path" : "agnostic/image-parse-v3", "storage" : "cloud", "ext" : "png", "time_out" : 30},
   {"id": 27, "app": "Parse_agnostic", "pos": "begin", "path" : "Parse_agnostic/agnostic/image-parse-v3", "storage" : "local", "ext" : "png", "time_out" : 30, "Case_ID" : "yes"},
   {"id": 28, "app": "Parse_agnostic", "pos": "begin", "path" : "agnostic/agnostic-v3.2", "storage" : "cloud", "ext" : "png", "time_out" : 240, "Case_ID" : "yes"},
   {"id": 29, "app": "Parse_agnostic", "pos": "begin", "path" : "agnostic/image-parse-agnostic-v3.2", "storage" : "cloud", "ext" : "png", "time_out" : 30, "Case_ID" : "yes"},
   {"id": 30, "app": "Ladi-Vton", "pos": "end", "foreign-id" : 5, "path" : "ladi_vton_input/test/cloth", "storage" : "cloud", "ext" : "jpg", "time_out" : 30},
   {"id": 31, "app": "Ladi-Vton", "pos": "end", "foreign-id" : 6, "path" : "ladi_vton_input/test/cloth-mask", "storage" : "cloud", "ext" : "jpg", "time_out" : 30},
   {"id": 32, "app": "Ladi-Vton", "pos": "end", "foreign-id" : 1, "path" : "ladi_vton_input/test/image", "storage" : "cloud", "ext" : "jpg", "time_out" : 30},
   {"id": 33, "app": "Ladi-Vton", "pos": "end", "foreign-id" : 23, "path" : "ladi_vton_input/test/image-densepose", "storage" : "cloud", "ext" : "png", "time_out" : 30, "Logging" : "yes"},
   {"id": 34, "app": "Ladi-Vton", "pos": "end", "foreign-id" : 19, "path" : "ladi_vton_input/test/image-parse-v3", "storage" : "cloud", "ext" : "png", "time_out" : 30},
   {"id": 35, "app": "Ladi-Vton", "pos": "end", "foreign-id" : 20, "path" : "ladi_vton_input/test/image-parse-v3-vis", "storage" : "cloud", "ext" : "png", "time_out" : 30, "Logging" : "yes"},
   {"id": 36, "app": "Ladi-Vton", "pos": "end", "foreign-id" : 11, "path" : "ladi_vton_input/test/openpose_img", "storage" : "cloud", "ext" : "png", "time_out" : 30, "Logging" : "yes"},
   {"id": 37, "app": "Ladi-Vton", "pos": "end", "foreign-id" : 12, "path" : "ladi_vton_input/test/openpose_json", "storage" : "cloud", "ext" : "json", "time_out" : 30},
   {"id": 39, "app": "Ladi-Vton", "pos": "end", "foreign-id" : 29, "path" : "ladi_vton_input/test/image-parse-agnostic-v3.2", "storage" : "cloud", "ext" : "png", "time_out" : 30},
   {"id": 40, "app": "Ladi-Vton", "pos": "end", "foreign-id" : 28, "path" : "ladi_vton_input/test/agnostic-v3.2", "storage" : "cloud", "ext" : "png", "time_out" : 30},
   {"id": 41, "app": "Ladi-Vton", "pos": "end", "foreign-id" : 4, "path" : "ladi_vton_input", "storage" : "cloud", "ext" : "txt", "time_out" : 30},
   {"id": 42, "app": "Ladi-Vton", "pos": "begin", "path" : "data/ladi_vton_input/test/image-parse-v3", "storage" : "local", "ext" : "png", "time_out" : 30, "Case_ID" : "yes"},
   {"id": 43, "app": "Ladi-Vton", "pos": "begin", "path" : "ladi_vton_output/unpaired/upper_body", "storage" : "cloud", "ext" : "png", "time_out" : 30, "Case_ID" : "yes"},
   {"id": 44, "app": "Ladi-Vton", "pos": "end", "foreign-id" : 43, "path" : "C:/Users/krisc/_tf2py310/FileSharing/Target", "storage" : "local", "ext" : "png", "LogicalName" : "VTON_image", "time_out" : 240}
]
